voice_robotifier/__init__.py
voice_robotifier/sapi.py
voice_robotifier/voice_robotifier.py
voice_robotifier/dectalk/MSVCRTd.DLL
voice_robotifier/dectalk/dectalk.dll
voice_robotifier/dectalk/dtalk_us.dic
voice_robotifier/dectalk/say.exe
voice_robotifier-1.1.dist-info/METADATA
voice_robotifier-1.1.dist-info/RECORD
voice_robotifier-1.1.dist-info/WHEEL
voice_robotifier-1.1.dist-info/top_level.txt
